adx_logging_handler/__init__.py
adx_logging_handler/adx_handler.py
adx_logging_handler/client.py
adx_logging_handler/ingest_client.py
adx_logging_handler-1.0.3.dist-info/LICENSE
adx_logging_handler-1.0.3.dist-info/METADATA
adx_logging_handler-1.0.3.dist-info/WHEEL
adx_logging_handler-1.0.3.dist-info/top_level.txt
adx_logging_handler-1.0.3.dist-info/RECORD
