Metadata-Version: 2.1
Name: adx-logging-handler
Version: 1.0.3
Summary: A python logging handler for Azure Data explorer
License-File: LICENSE
Requires-Dist: azure-kusto-data
Requires-Dist: azure-kusto-ingest
